cospar/__init__.py
cospar/datasets.py
cospar/help_functions/__init__.py
cospar/help_functions/_docs.py
cospar/help_functions/_help_functions_CoSpar.py
cospar/hf.py
cospar/logging.py
cospar/pl.py
cospar/plotting/__init__.py
cospar/plotting/_clone.py
cospar/plotting/_gene.py
cospar/plotting/_map.py
cospar/plotting/_utils.py
cospar/pp.py
cospar/preprocessing/__init__.py
cospar/preprocessing/_preprocessing.py
cospar/settings.py
cospar/simulate.py
cospar/tl.py
cospar/tmap/__init__.py
cospar/tmap/_tmap_core.py
cospar/tmap/_utils.py
cospar/tmap/map_reconstruction.py
cospar/tmap/optimal_transport.py
cospar/tool/__init__.py
cospar/tool/_clone.py
cospar/tool/_gene.py
cospar/tool/_map.py
cospar/tool/_utils.py
cospar-0.4.1.dist-info/LICENSE
cospar-0.4.1.dist-info/METADATA
cospar-0.4.1.dist-info/WHEEL
cospar-0.4.1.dist-info/RECORD
