Metadata-Version: 2.1
Name: cospar
Version: 0.4.1
Summary: A toolkit for dynamic inference of cell fate by integrating state and lineage information.
Home-page: https://github.com/ShouWenWang-Lab/cospar
Keywords: cell fate,differentiation,dynamic inference,lineage tracing,transcriptomics
Author: Shou-Wen Wang
Author-email: wangshouwen@westlake.edu.cn
Requires-Python: >=3.9,<3.12
Classifier: Development Status :: 5 - Production/Stable
Classifier: Intended Audience :: Science/Research
Classifier: Programming Language :: Python :: 3
Classifier: Programming Language :: Python :: 3.9
Classifier: Programming Language :: Python :: 3.10
Classifier: Programming Language :: Python :: 3.11
Classifier: Topic :: Scientific/Engineering :: Bio-Informatics
Classifier: Topic :: Scientific/Engineering :: Visualization
Requires-Dist: anndata (>=0.9.2,<0.10.0)
Requires-Dist: ete3 (>=3.1.3,<4.0.0)
Requires-Dist: fastcluster (>=1.2.6,<2.0.0)
Requires-Dist: gseapy (>=1.1.3,<2.0.0)
Requires-Dist: leidenalg (>=0.10.2,<0.11.0)
Requires-Dist: matplotlib (>=3.7.3,<3.8.0)
Requires-Dist: numpy (>=1.24.4,<2.0.0)
Requires-Dist: pandas (>=2.0.3,<3.0.0)
Requires-Dist: plotnine (>=0.12.4,<0.13.0)
Requires-Dist: scanpy (>=1.9.8,<2.0.0)
Requires-Dist: scikit-learn (>=1.1.3,<1.2.0)
Requires-Dist: scikit-misc (>=0.1.4,<0.3.0)
Requires-Dist: scipy (>=1.10.1,<2.0.0)
Requires-Dist: statsmodels (>=0.14.2,<0.15.0)
Requires-Dist: tqdm (>=4.66.5,<5.0.0)
Project-URL: Documentation, https://cospar.readthedocs.io/
Project-URL: Repository, https://github.com/ShouWenWang-Lab/cospar
